{
  "version": "world_cup_2026.team_values.v1",
  "source_policy": "real reviewed mappings only; no scraping, no credentials, no market-derived values",
  "source_note": "Transfermarkt WC2026 squad totals via planetfootball (2026-06-27). team_id = stable API-Football ids extracted from repo raw fixtures. This artifact has not been re-verified against the Transfermarkt primary page; entries are graded as secondary_with_primary_reference with confidence capped at 0.85.",
  "items": [
    {
      "team_id": "2",
      "team_name": "France",
      "squad_value_eur": 1520000000,
      "currency": "EUR",
      "observed_at": "2026-06-27T00:00:00Z",
      "source_system": "transfermarkt",
      "source_url": "https://www.planetfootball.com/lists-and-rankings/world-cup-2026-every-squad-ranked-market-value",
      "primary_source": "https://www.transfermarkt.com/weltmeisterschaft/teilnehmer/pokalwettbewerb/FIWC/saison_id/2025",
      "confidence": 0.85,
      "reviewed_by": "liudehua",
      "source_tier": "secondary_with_primary_reference",
      "primary_source_review_status": "pending_primary_review",
      "confidence_reason": "Secondary published list citing Transfermarkt; not directly re-verified against primary source in this artifact."
    },
    {
      "team_id": "10",
      "team_name": "England",
      "squad_value_eur": 1360000000,
      "currency": "EUR",
      "observed_at": "2026-06-27T00:00:00Z",
      "source_system": "transfermarkt",
      "source_url": "https://www.planetfootball.com/lists-and-rankings/world-cup-2026-every-squad-ranked-market-value",
      "primary_source": "https://www.transfermarkt.com/weltmeisterschaft/teilnehmer/pokalwettbewerb/FIWC/saison_id/2025",
      "confidence": 0.85,
      "reviewed_by": "liudehua",
      "source_tier": "secondary_with_primary_reference",
      "primary_source_review_status": "pending_primary_review",
      "confidence_reason": "Secondary published list citing Transfermarkt; not directly re-verified against primary source in this artifact."
    },
    {
      "team_id": "9",
      "team_name": "Spain",
      "squad_value_eur": 1220000000,
      "currency": "EUR",
      "observed_at": "2026-06-27T00:00:00Z",
      "source_system": "transfermarkt",
      "source_url": "https://www.planetfootball.com/lists-and-rankings/world-cup-2026-every-squad-ranked-market-value",
      "primary_source": "https://www.transfermarkt.com/weltmeisterschaft/teilnehmer/pokalwettbewerb/FIWC/saison_id/2025",
      "confidence": 0.85,
      "reviewed_by": "liudehua",
      "source_tier": "secondary_with_primary_reference",
      "primary_source_review_status": "pending_primary_review",
      "confidence_reason": "Secondary published list citing Transfermarkt; not directly re-verified against primary source in this artifact."
    },
    {
      "team_id": "27",
      "team_name": "Portugal",
      "squad_value_eur": 1010000000,
      "currency": "EUR",
      "observed_at": "2026-06-27T00:00:00Z",
      "source_system": "transfermarkt",
      "source_url": "https://www.planetfootball.com/lists-and-rankings/world-cup-2026-every-squad-ranked-market-value",
      "primary_source": "https://www.transfermarkt.com/weltmeisterschaft/teilnehmer/pokalwettbewerb/FIWC/saison_id/2025",
      "confidence": 0.85,
      "reviewed_by": "liudehua",
      "source_tier": "secondary_with_primary_reference",
      "primary_source_review_status": "pending_primary_review",
      "confidence_reason": "Secondary published list citing Transfermarkt; not directly re-verified against primary source in this artifact."
    },
    {
      "team_id": "25",
      "team_name": "Germany",
      "squad_value_eur": 947000000,
      "currency": "EUR",
      "observed_at": "2026-06-27T00:00:00Z",
      "source_system": "transfermarkt",
      "source_url": "https://www.planetfootball.com/lists-and-rankings/world-cup-2026-every-squad-ranked-market-value",
      "primary_source": "https://www.transfermarkt.com/weltmeisterschaft/teilnehmer/pokalwettbewerb/FIWC/saison_id/2025",
      "confidence": 0.85,
      "reviewed_by": "liudehua",
      "source_tier": "secondary_with_primary_reference",
      "primary_source_review_status": "pending_primary_review",
      "confidence_reason": "Secondary published list citing Transfermarkt; not directly re-verified against primary source in this artifact."
    },
    {
      "team_id": "6",
      "team_name": "Brazil",
      "squad_value_eur": 928200000,
      "currency": "EUR",
      "observed_at": "2026-06-27T00:00:00Z",
      "source_system": "transfermarkt",
      "source_url": "https://www.planetfootball.com/lists-and-rankings/world-cup-2026-every-squad-ranked-market-value",
      "primary_source": "https://www.transfermarkt.com/weltmeisterschaft/teilnehmer/pokalwettbewerb/FIWC/saison_id/2025",
      "confidence": 0.85,
      "reviewed_by": "liudehua",
      "source_tier": "secondary_with_primary_reference",
      "primary_source_review_status": "pending_primary_review",
      "confidence_reason": "Secondary published list citing Transfermarkt; not directly re-verified against primary source in this artifact."
    },
    {
      "team_id": "26",
      "team_name": "Argentina",
      "squad_value_eur": 807500000,
      "currency": "EUR",
      "observed_at": "2026-06-27T00:00:00Z",
      "source_system": "transfermarkt",
      "source_url": "https://www.planetfootball.com/lists-and-rankings/world-cup-2026-every-squad-ranked-market-value",
      "primary_source": "https://www.transfermarkt.com/weltmeisterschaft/teilnehmer/pokalwettbewerb/FIWC/saison_id/2025",
      "confidence": 0.85,
      "reviewed_by": "liudehua",
      "source_tier": "secondary_with_primary_reference",
      "primary_source_review_status": "pending_primary_review",
      "confidence_reason": "Secondary published list citing Transfermarkt; not directly re-verified against primary source in this artifact."
    },
    {
      "team_id": "1118",
      "team_name": "Netherlands",
      "squad_value_eur": 754200000,
      "currency": "EUR",
      "observed_at": "2026-06-27T00:00:00Z",
      "source_system": "transfermarkt",
      "source_url": "https://www.planetfootball.com/lists-and-rankings/world-cup-2026-every-squad-ranked-market-value",
      "primary_source": "https://www.transfermarkt.com/weltmeisterschaft/teilnehmer/pokalwettbewerb/FIWC/saison_id/2025",
      "confidence": 0.85,
      "reviewed_by": "liudehua",
      "source_tier": "secondary_with_primary_reference",
      "primary_source_review_status": "pending_primary_review",
      "confidence_reason": "Secondary published list citing Transfermarkt; not directly re-verified against primary source in this artifact."
    },
    {
      "team_id": "1",
      "team_name": "Belgium",
      "squad_value_eur": 547500000,
      "currency": "EUR",
      "observed_at": "2026-06-27T00:00:00Z",
      "source_system": "transfermarkt",
      "source_url": "https://www.planetfootball.com/lists-and-rankings/world-cup-2026-every-squad-ranked-market-value",
      "primary_source": "https://www.transfermarkt.com/weltmeisterschaft/teilnehmer/pokalwettbewerb/FIWC/saison_id/2025",
      "confidence": 0.85,
      "reviewed_by": "liudehua",
      "source_tier": "secondary_with_primary_reference",
      "primary_source_review_status": "pending_primary_review",
      "confidence_reason": "Secondary published list citing Transfermarkt; not directly re-verified against primary source in this artifact."
    },
    {
      "team_id": "1501",
      "team_name": "Ivory Coast",
      "squad_value_eur": 522100000,
      "currency": "EUR",
      "observed_at": "2026-06-27T00:00:00Z",
      "source_system": "transfermarkt",
      "source_url": "https://www.planetfootball.com/lists-and-rankings/world-cup-2026-every-squad-ranked-market-value",
      "primary_source": "https://www.transfermarkt.com/weltmeisterschaft/teilnehmer/pokalwettbewerb/FIWC/saison_id/2025",
      "confidence": 0.85,
      "reviewed_by": "liudehua",
      "source_tier": "secondary_with_primary_reference",
      "primary_source_review_status": "pending_primary_review",
      "confidence_reason": "Secondary published list citing Transfermarkt; not directly re-verified against primary source in this artifact."
    },
    {
      "team_id": "13",
      "team_name": "Senegal",
      "squad_value_eur": 478100000,
      "currency": "EUR",
      "observed_at": "2026-06-27T00:00:00Z",
      "source_system": "transfermarkt",
      "source_url": "https://www.planetfootball.com/lists-and-rankings/world-cup-2026-every-squad-ranked-market-value",
      "primary_source": "https://www.transfermarkt.com/weltmeisterschaft/teilnehmer/pokalwettbewerb/FIWC/saison_id/2025",
      "confidence": 0.85,
      "reviewed_by": "liudehua",
      "source_tier": "secondary_with_primary_reference",
      "primary_source_review_status": "pending_primary_review",
      "confidence_reason": "Secondary published list citing Transfermarkt; not directly re-verified against primary source in this artifact."
    },
    {
      "team_id": "31",
      "team_name": "Morocco",
      "squad_value_eur": 447700000,
      "currency": "EUR",
      "observed_at": "2026-06-27T00:00:00Z",
      "source_system": "transfermarkt",
      "source_url": "https://www.planetfootball.com/lists-and-rankings/world-cup-2026-every-squad-ranked-market-value",
      "primary_source": "https://www.transfermarkt.com/weltmeisterschaft/teilnehmer/pokalwettbewerb/FIWC/saison_id/2025",
      "confidence": 0.85,
      "reviewed_by": "liudehua",
      "source_tier": "secondary_with_primary_reference",
      "primary_source_review_status": "pending_primary_review",
      "confidence_reason": "Secondary published list citing Transfermarkt; not directly re-verified against primary source in this artifact."
    },
    {
      "team_id": "5",
      "team_name": "Sweden",
      "squad_value_eur": 406080000,
      "currency": "EUR",
      "observed_at": "2026-06-27T00:00:00Z",
      "source_system": "transfermarkt",
      "source_url": "https://www.planetfootball.com/lists-and-rankings/world-cup-2026-every-squad-ranked-market-value",
      "primary_source": "https://www.transfermarkt.com/weltmeisterschaft/teilnehmer/pokalwettbewerb/FIWC/saison_id/2025",
      "confidence": 0.85,
      "reviewed_by": "liudehua",
      "source_tier": "secondary_with_primary_reference",
      "primary_source_review_status": "pending_primary_review",
      "confidence_reason": "Secondary published list citing Transfermarkt; not directly re-verified against primary source in this artifact."
    },
    {
      "team_id": "3",
      "team_name": "Croatia",
      "squad_value_eur": 387300000,
      "currency": "EUR",
      "observed_at": "2026-06-27T00:00:00Z",
      "source_system": "transfermarkt",
      "source_url": "https://www.planetfootball.com/lists-and-rankings/world-cup-2026-every-squad-ranked-market-value",
      "primary_source": "https://www.transfermarkt.com/weltmeisterschaft/teilnehmer/pokalwettbewerb/FIWC/saison_id/2025",
      "confidence": 0.85,
      "reviewed_by": "liudehua",
      "source_tier": "secondary_with_primary_reference",
      "primary_source_review_status": "pending_primary_review",
      "confidence_reason": "Secondary published list citing Transfermarkt; not directly re-verified against primary source in this artifact."
    },
    {
      "team_id": "2384",
      "team_name": "United States",
      "squad_value_eur": 385600000,
      "currency": "EUR",
      "observed_at": "2026-06-27T00:00:00Z",
      "source_system": "transfermarkt",
      "source_url": "https://www.planetfootball.com/lists-and-rankings/world-cup-2026-every-squad-ranked-market-value",
      "primary_source": "https://www.transfermarkt.com/weltmeisterschaft/teilnehmer/pokalwettbewerb/FIWC/saison_id/2025",
      "confidence": 0.85,
      "reviewed_by": "liudehua",
      "source_tier": "secondary_with_primary_reference",
      "primary_source_review_status": "pending_primary_review",
      "confidence_reason": "Secondary published list citing Transfermarkt; not directly re-verified against primary source in this artifact."
    },
    {
      "team_id": "2382",
      "team_name": "Ecuador",
      "squad_value_eur": 368700000,
      "currency": "EUR",
      "observed_at": "2026-06-27T00:00:00Z",
      "source_system": "transfermarkt",
      "source_url": "https://www.planetfootball.com/lists-and-rankings/world-cup-2026-every-squad-ranked-market-value",
      "primary_source": "https://www.transfermarkt.com/weltmeisterschaft/teilnehmer/pokalwettbewerb/FIWC/saison_id/2025",
      "confidence": 0.85,
      "reviewed_by": "liudehua",
      "source_tier": "secondary_with_primary_reference",
      "primary_source_review_status": "pending_primary_review",
      "confidence_reason": "Secondary published list citing Transfermarkt; not directly re-verified against primary source in this artifact."
    },
    {
      "team_id": "7",
      "team_name": "Uruguay",
      "squad_value_eur": 359300000,
      "currency": "EUR",
      "observed_at": "2026-06-27T00:00:00Z",
      "source_system": "transfermarkt",
      "source_url": "https://www.planetfootball.com/lists-and-rankings/world-cup-2026-every-squad-ranked-market-value",
      "primary_source": "https://www.transfermarkt.com/weltmeisterschaft/teilnehmer/pokalwettbewerb/FIWC/saison_id/2025",
      "confidence": 0.85,
      "reviewed_by": "liudehua",
      "source_tier": "secondary_with_primary_reference",
      "primary_source_review_status": "pending_primary_review",
      "confidence_reason": "Secondary published list citing Transfermarkt; not directly re-verified against primary source in this artifact."
    },
    {
      "team_id": "15",
      "team_name": "Switzerland",
      "squad_value_eur": 332500000,
      "currency": "EUR",
      "observed_at": "2026-06-27T00:00:00Z",
      "source_system": "transfermarkt",
      "source_url": "https://www.planetfootball.com/lists-and-rankings/world-cup-2026-every-squad-ranked-market-value",
      "primary_source": "https://www.transfermarkt.com/weltmeisterschaft/teilnehmer/pokalwettbewerb/FIWC/saison_id/2025",
      "confidence": 0.85,
      "reviewed_by": "liudehua",
      "source_tier": "secondary_with_primary_reference",
      "primary_source_review_status": "pending_primary_review",
      "confidence_reason": "Secondary published list citing Transfermarkt; not directly re-verified against primary source in this artifact."
    },
    {
      "team_id": "8",
      "team_name": "Colombia",
      "squad_value_eur": 302350000,
      "currency": "EUR",
      "observed_at": "2026-06-27T00:00:00Z",
      "source_system": "transfermarkt",
      "source_url": "https://www.planetfootball.com/lists-and-rankings/world-cup-2026-every-squad-ranked-market-value",
      "primary_source": "https://www.transfermarkt.com/weltmeisterschaft/teilnehmer/pokalwettbewerb/FIWC/saison_id/2025",
      "confidence": 0.85,
      "reviewed_by": "liudehua",
      "source_tier": "secondary_with_primary_reference",
      "primary_source_review_status": "pending_primary_review",
      "confidence_reason": "Secondary published list citing Transfermarkt; not directly re-verified against primary source in this artifact."
    },
    {
      "team_id": "12",
      "team_name": "Japan",
      "squad_value_eur": 270850000,
      "currency": "EUR",
      "observed_at": "2026-06-27T00:00:00Z",
      "source_system": "transfermarkt",
      "source_url": "https://www.planetfootball.com/lists-and-rankings/world-cup-2026-every-squad-ranked-market-value",
      "primary_source": "https://www.transfermarkt.com/weltmeisterschaft/teilnehmer/pokalwettbewerb/FIWC/saison_id/2025",
      "confidence": 0.85,
      "reviewed_by": "liudehua",
      "source_tier": "secondary_with_primary_reference",
      "primary_source_review_status": "pending_primary_review",
      "confidence_reason": "Secondary published list citing Transfermarkt; not directly re-verified against primary source in this artifact."
    },
    {
      "team_id": "1532",
      "team_name": "Algeria",
      "squad_value_eur": 256900000,
      "currency": "EUR",
      "observed_at": "2026-06-27T00:00:00Z",
      "source_system": "transfermarkt",
      "source_url": "https://www.planetfootball.com/lists-and-rankings/world-cup-2026-every-squad-ranked-market-value",
      "primary_source": "https://www.transfermarkt.com/weltmeisterschaft/teilnehmer/pokalwettbewerb/FIWC/saison_id/2025",
      "confidence": 0.85,
      "reviewed_by": "liudehua",
      "source_tier": "secondary_with_primary_reference",
      "primary_source_review_status": "pending_primary_review",
      "confidence_reason": "Secondary published list citing Transfermarkt; not directly re-verified against primary source in this artifact."
    },
    {
      "team_id": "1504",
      "team_name": "Ghana",
      "squad_value_eur": 234500000,
      "currency": "EUR",
      "observed_at": "2026-06-27T00:00:00Z",
      "source_system": "transfermarkt",
      "source_url": "https://www.planetfootball.com/lists-and-rankings/world-cup-2026-every-squad-ranked-market-value",
      "primary_source": "https://www.transfermarkt.com/weltmeisterschaft/teilnehmer/pokalwettbewerb/FIWC/saison_id/2025",
      "confidence": 0.85,
      "reviewed_by": "liudehua",
      "source_tier": "secondary_with_primary_reference",
      "primary_source_review_status": "pending_primary_review",
      "confidence_reason": "Secondary published list citing Transfermarkt; not directly re-verified against primary source in this artifact."
    },
    {
      "team_id": "5529",
      "team_name": "Canada",
      "squad_value_eur": 198650000,
      "currency": "EUR",
      "observed_at": "2026-06-27T00:00:00Z",
      "source_system": "transfermarkt",
      "source_url": "https://www.planetfootball.com/lists-and-rankings/world-cup-2026-every-squad-ranked-market-value",
      "primary_source": "https://www.transfermarkt.com/weltmeisterschaft/teilnehmer/pokalwettbewerb/FIWC/saison_id/2025",
      "confidence": 0.85,
      "reviewed_by": "liudehua",
      "source_tier": "secondary_with_primary_reference",
      "primary_source_review_status": "pending_primary_review",
      "confidence_reason": "Secondary published list citing Transfermarkt; not directly re-verified against primary source in this artifact."
    },
    {
      "team_id": "16",
      "team_name": "Mexico",
      "squad_value_eur": 191850000,
      "currency": "EUR",
      "observed_at": "2026-06-27T00:00:00Z",
      "source_system": "transfermarkt",
      "source_url": "https://www.planetfootball.com/lists-and-rankings/world-cup-2026-every-squad-ranked-market-value",
      "primary_source": "https://www.transfermarkt.com/weltmeisterschaft/teilnehmer/pokalwettbewerb/FIWC/saison_id/2025",
      "confidence": 0.85,
      "reviewed_by": "liudehua",
      "source_tier": "secondary_with_primary_reference",
      "primary_source_review_status": "pending_primary_review",
      "confidence_reason": "Secondary published list citing Transfermarkt; not directly re-verified against primary source in this artifact."
    },
    {
      "team_id": "1113",
      "team_name": "Bosnia & Herzegovina",
      "squad_value_eur": 146400000,
      "currency": "EUR",
      "observed_at": "2026-06-27T00:00:00Z",
      "source_system": "transfermarkt",
      "source_url": "https://www.planetfootball.com/lists-and-rankings/world-cup-2026-every-squad-ranked-market-value",
      "primary_source": "https://www.transfermarkt.com/weltmeisterschaft/teilnehmer/pokalwettbewerb/FIWC/saison_id/2025",
      "confidence": 0.85,
      "reviewed_by": "liudehua",
      "source_tier": "secondary_with_primary_reference",
      "primary_source_review_status": "pending_primary_review",
      "confidence_reason": "Secondary published list citing Transfermarkt; not directly re-verified against primary source in this artifact."
    },
    {
      "team_id": "17",
      "team_name": "South Korea",
      "squad_value_eur": 139050000,
      "currency": "EUR",
      "observed_at": "2026-06-27T00:00:00Z",
      "source_system": "transfermarkt",
      "source_url": "https://www.planetfootball.com/lists-and-rankings/world-cup-2026-every-squad-ranked-market-value",
      "primary_source": "https://www.transfermarkt.com/weltmeisterschaft/teilnehmer/pokalwettbewerb/FIWC/saison_id/2025",
      "confidence": 0.85,
      "reviewed_by": "liudehua",
      "source_tier": "secondary_with_primary_reference",
      "primary_source_review_status": "pending_primary_review",
      "confidence_reason": "Secondary published list citing Transfermarkt; not directly re-verified against primary source in this artifact."
    },
    {
      "team_id": "32",
      "team_name": "Egypt",
      "squad_value_eur": 116480000,
      "currency": "EUR",
      "observed_at": "2026-06-27T00:00:00Z",
      "source_system": "transfermarkt",
      "source_url": "https://www.planetfootball.com/lists-and-rankings/world-cup-2026-every-squad-ranked-market-value",
      "primary_source": "https://www.transfermarkt.com/weltmeisterschaft/teilnehmer/pokalwettbewerb/FIWC/saison_id/2025",
      "confidence": 0.85,
      "reviewed_by": "liudehua",
      "source_tier": "secondary_with_primary_reference",
      "primary_source_review_status": "pending_primary_review",
      "confidence_reason": "Secondary published list citing Transfermarkt; not directly re-verified against primary source in this artifact."
    },
    {
      "team_id": "20",
      "team_name": "Australia",
      "squad_value_eur": 77450000,
      "currency": "EUR",
      "observed_at": "2026-06-27T00:00:00Z",
      "source_system": "transfermarkt",
      "source_url": "https://www.planetfootball.com/lists-and-rankings/world-cup-2026-every-squad-ranked-market-value",
      "primary_source": "https://www.transfermarkt.com/weltmeisterschaft/teilnehmer/pokalwettbewerb/FIWC/saison_id/2025",
      "confidence": 0.85,
      "reviewed_by": "liudehua",
      "source_tier": "secondary_with_primary_reference",
      "primary_source_review_status": "pending_primary_review",
      "confidence_reason": "Secondary published list citing Transfermarkt; not directly re-verified against primary source in this artifact."
    },
    {
      "team_id": "28",
      "team_name": "Tunisia",
      "squad_value_eur": 69950000,
      "currency": "EUR",
      "observed_at": "2026-06-27T00:00:00Z",
      "source_system": "transfermarkt",
      "source_url": "https://www.planetfootball.com/lists-and-rankings/world-cup-2026-every-squad-ranked-market-value",
      "primary_source": "https://www.transfermarkt.com/weltmeisterschaft/teilnehmer/pokalwettbewerb/FIWC/saison_id/2025",
      "confidence": 0.85,
      "reviewed_by": "liudehua",
      "source_tier": "secondary_with_primary_reference",
      "primary_source_review_status": "pending_primary_review",
      "confidence_reason": "Secondary published list citing Transfermarkt; not directly re-verified against primary source in this artifact."
    },
    {
      "team_id": "23",
      "team_name": "Saudi Arabia",
      "squad_value_eur": 40680000,
      "currency": "EUR",
      "observed_at": "2026-06-27T00:00:00Z",
      "source_system": "transfermarkt",
      "source_url": "https://www.planetfootball.com/lists-and-rankings/world-cup-2026-every-squad-ranked-market-value",
      "primary_source": "https://www.transfermarkt.com/weltmeisterschaft/teilnehmer/pokalwettbewerb/FIWC/saison_id/2025",
      "confidence": 0.85,
      "reviewed_by": "liudehua",
      "source_tier": "secondary_with_primary_reference",
      "primary_source_review_status": "pending_primary_review",
      "confidence_reason": "Secondary published list citing Transfermarkt; not directly re-verified against primary source in this artifact."
    },
    {
      "team_id": "11",
      "team_name": "Panama",
      "squad_value_eur": 34550000,
      "currency": "EUR",
      "observed_at": "2026-06-27T00:00:00Z",
      "source_system": "transfermarkt",
      "source_url": "https://www.planetfootball.com/lists-and-rankings/world-cup-2026-every-squad-ranked-market-value",
      "primary_source": "https://www.transfermarkt.com/weltmeisterschaft/teilnehmer/pokalwettbewerb/FIWC/saison_id/2025",
      "confidence": 0.85,
      "reviewed_by": "liudehua",
      "source_tier": "secondary_with_primary_reference",
      "primary_source_review_status": "pending_primary_review",
      "confidence_reason": "Secondary published list citing Transfermarkt; not directly re-verified against primary source in this artifact."
    },
    {
      "team_id": "22",
      "team_name": "Iran",
      "squad_value_eur": 32050000,
      "currency": "EUR",
      "observed_at": "2026-06-27T00:00:00Z",
      "source_system": "transfermarkt",
      "source_url": "https://www.planetfootball.com/lists-and-rankings/world-cup-2026-every-squad-ranked-market-value",
      "primary_source": "https://www.transfermarkt.com/weltmeisterschaft/teilnehmer/pokalwettbewerb/FIWC/saison_id/2025",
      "confidence": 0.85,
      "reviewed_by": "liudehua",
      "source_tier": "secondary_with_primary_reference",
      "primary_source_review_status": "pending_primary_review",
      "confidence_reason": "Secondary published list citing Transfermarkt; not directly re-verified against primary source in this artifact."
    },
    {
      "team_id": "1569",
      "team_name": "Qatar",
      "squad_value_eur": 19930000,
      "currency": "EUR",
      "observed_at": "2026-06-27T00:00:00Z",
      "source_system": "transfermarkt",
      "source_url": "https://www.planetfootball.com/lists-and-rankings/world-cup-2026-every-squad-ranked-market-value",
      "primary_source": "https://www.transfermarkt.com/weltmeisterschaft/teilnehmer/pokalwettbewerb/FIWC/saison_id/2025",
      "confidence": 0.85,
      "reviewed_by": "liudehua",
      "source_tier": "secondary_with_primary_reference",
      "primary_source_review_status": "pending_primary_review",
      "confidence_reason": "Secondary published list citing Transfermarkt; not directly re-verified against primary source in this artifact."
    },
    {
      "team_id": "1090",
      "team_name": "Norway",
      "squad_value_eur": 589900000,
      "currency": "EUR",
      "observed_at": "2026-06-27T00:00:00Z",
      "source_system": "transfermarkt",
      "source_url": "https://www.planetfootball.com/lists-and-rankings/world-cup-2026-every-squad-ranked-market-value",
      "primary_source": "https://www.transfermarkt.com/weltmeisterschaft/teilnehmer/pokalwettbewerb/FIWC/saison_id/2025",
      "confidence": 0.85,
      "reviewed_by": "liudehua",
      "source_tier": "secondary_with_primary_reference",
      "primary_source_review_status": "pending_primary_review",
      "confidence_reason": "Secondary published list citing Transfermarkt; not directly re-verified against primary source in this artifact."
    },
    {
      "team_id": "777",
      "team_name": "Turkey (Türkiye)",
      "squad_value_eur": 473700000,
      "currency": "EUR",
      "observed_at": "2026-06-27T00:00:00Z",
      "source_system": "transfermarkt",
      "source_url": "https://www.planetfootball.com/lists-and-rankings/world-cup-2026-every-squad-ranked-market-value",
      "primary_source": "https://www.transfermarkt.com/weltmeisterschaft/teilnehmer/pokalwettbewerb/FIWC/saison_id/2025",
      "confidence": 0.85,
      "reviewed_by": "liudehua",
      "source_tier": "secondary_with_primary_reference",
      "primary_source_review_status": "pending_primary_review",
      "confidence_reason": "Secondary published list citing Transfermarkt; not directly re-verified against primary source in this artifact."
    },
    {
      "team_id": "775",
      "team_name": "Austria",
      "squad_value_eur": 245200000,
      "currency": "EUR",
      "observed_at": "2026-06-27T00:00:00Z",
      "source_system": "transfermarkt",
      "source_url": "https://www.planetfootball.com/lists-and-rankings/world-cup-2026-every-squad-ranked-market-value",
      "primary_source": "https://www.transfermarkt.com/weltmeisterschaft/teilnehmer/pokalwettbewerb/FIWC/saison_id/2025",
      "confidence": 0.85,
      "reviewed_by": "liudehua",
      "source_tier": "secondary_with_primary_reference",
      "primary_source_review_status": "pending_primary_review",
      "confidence_reason": "Secondary published list citing Transfermarkt; not directly re-verified against primary source in this artifact."
    },
    {
      "team_id": "770",
      "team_name": "Czech Republic (Czechia)",
      "squad_value_eur": 188180000,
      "currency": "EUR",
      "observed_at": "2026-06-27T00:00:00Z",
      "source_system": "transfermarkt",
      "source_url": "https://www.planetfootball.com/lists-and-rankings/world-cup-2026-every-squad-ranked-market-value",
      "primary_source": "https://www.transfermarkt.com/weltmeisterschaft/teilnehmer/pokalwettbewerb/FIWC/saison_id/2025",
      "confidence": 0.85,
      "reviewed_by": "liudehua",
      "source_tier": "secondary_with_primary_reference",
      "primary_source_review_status": "pending_primary_review",
      "confidence_reason": "Secondary published list citing Transfermarkt; not directly re-verified against primary source in this artifact."
    },
    {
      "team_id": "1108",
      "team_name": "Scotland",
      "squad_value_eur": 170250000,
      "currency": "EUR",
      "observed_at": "2026-06-27T00:00:00Z",
      "source_system": "transfermarkt",
      "source_url": "https://www.planetfootball.com/lists-and-rankings/world-cup-2026-every-squad-ranked-market-value",
      "primary_source": "https://www.transfermarkt.com/weltmeisterschaft/teilnehmer/pokalwettbewerb/FIWC/saison_id/2025",
      "confidence": 0.85,
      "reviewed_by": "liudehua",
      "source_tier": "secondary_with_primary_reference",
      "primary_source_review_status": "pending_primary_review",
      "confidence_reason": "Secondary published list citing Transfermarkt; not directly re-verified against primary source in this artifact."
    },
    {
      "team_id": "2380",
      "team_name": "Paraguay",
      "squad_value_eur": 153650000,
      "currency": "EUR",
      "observed_at": "2026-06-27T00:00:00Z",
      "source_system": "transfermarkt",
      "source_url": "https://www.planetfootball.com/lists-and-rankings/world-cup-2026-every-squad-ranked-market-value",
      "primary_source": "https://www.transfermarkt.com/weltmeisterschaft/teilnehmer/pokalwettbewerb/FIWC/saison_id/2025",
      "confidence": 0.85,
      "reviewed_by": "liudehua",
      "source_tier": "secondary_with_primary_reference",
      "primary_source_review_status": "pending_primary_review",
      "confidence_reason": "Secondary published list citing Transfermarkt; not directly re-verified against primary source in this artifact."
    },
    {
      "team_id": "1508",
      "team_name": "DR Congo (Congo DR)",
      "squad_value_eur": 143900000,
      "currency": "EUR",
      "observed_at": "2026-06-27T00:00:00Z",
      "source_system": "transfermarkt",
      "source_url": "https://www.planetfootball.com/lists-and-rankings/world-cup-2026-every-squad-ranked-market-value",
      "primary_source": "https://www.transfermarkt.com/weltmeisterschaft/teilnehmer/pokalwettbewerb/FIWC/saison_id/2025",
      "confidence": 0.85,
      "reviewed_by": "liudehua",
      "source_tier": "secondary_with_primary_reference",
      "primary_source_review_status": "pending_primary_review",
      "confidence_reason": "Secondary published list citing Transfermarkt; not directly re-verified against primary source in this artifact."
    },
    {
      "team_id": "1568",
      "team_name": "Uzbekistan",
      "squad_value_eur": 85330000,
      "currency": "EUR",
      "observed_at": "2026-06-27T00:00:00Z",
      "source_system": "transfermarkt",
      "source_url": "https://www.planetfootball.com/lists-and-rankings/world-cup-2026-every-squad-ranked-market-value",
      "primary_source": "https://www.transfermarkt.com/weltmeisterschaft/teilnehmer/pokalwettbewerb/FIWC/saison_id/2025",
      "confidence": 0.85,
      "reviewed_by": "liudehua",
      "source_tier": "secondary_with_primary_reference",
      "primary_source_review_status": "pending_primary_review",
      "confidence_reason": "Secondary published list citing Transfermarkt; not directly re-verified against primary source in this artifact."
    },
    {
      "team_id": "2386",
      "team_name": "Haiti",
      "squad_value_eur": 55900000,
      "currency": "EUR",
      "observed_at": "2026-06-27T00:00:00Z",
      "source_system": "transfermarkt",
      "source_url": "https://www.planetfootball.com/lists-and-rankings/world-cup-2026-every-squad-ranked-market-value",
      "primary_source": "https://www.transfermarkt.com/weltmeisterschaft/teilnehmer/pokalwettbewerb/FIWC/saison_id/2025",
      "confidence": 0.85,
      "reviewed_by": "liudehua",
      "source_tier": "secondary_with_primary_reference",
      "primary_source_review_status": "pending_primary_review",
      "confidence_reason": "Secondary published list citing Transfermarkt; not directly re-verified against primary source in this artifact."
    },
    {
      "team_id": "1533",
      "team_name": "Cape Verde (Cabo Verde)",
      "squad_value_eur": 49250000,
      "currency": "EUR",
      "observed_at": "2026-06-27T00:00:00Z",
      "source_system": "transfermarkt",
      "source_url": "https://www.planetfootball.com/lists-and-rankings/world-cup-2026-every-squad-ranked-market-value",
      "primary_source": "https://www.transfermarkt.com/weltmeisterschaft/teilnehmer/pokalwettbewerb/FIWC/saison_id/2025",
      "confidence": 0.85,
      "reviewed_by": "liudehua",
      "source_tier": "secondary_with_primary_reference",
      "primary_source_review_status": "pending_primary_review",
      "confidence_reason": "Secondary published list citing Transfermarkt; not directly re-verified against primary source in this artifact."
    },
    {
      "team_id": "1531",
      "team_name": "South Africa",
      "squad_value_eur": 49250000,
      "currency": "EUR",
      "observed_at": "2026-06-27T00:00:00Z",
      "source_system": "transfermarkt",
      "source_url": "https://www.planetfootball.com/lists-and-rankings/world-cup-2026-every-squad-ranked-market-value",
      "primary_source": "https://www.transfermarkt.com/weltmeisterschaft/teilnehmer/pokalwettbewerb/FIWC/saison_id/2025",
      "confidence": 0.85,
      "reviewed_by": "liudehua",
      "source_tier": "secondary_with_primary_reference",
      "primary_source_review_status": "pending_primary_review",
      "confidence_reason": "Secondary published list citing Transfermarkt; not directly re-verified against primary source in this artifact."
    },
    {
      "team_id": "4673",
      "team_name": "New Zealand",
      "squad_value_eur": 34450000,
      "currency": "EUR",
      "observed_at": "2026-06-27T00:00:00Z",
      "source_system": "transfermarkt",
      "source_url": "https://www.planetfootball.com/lists-and-rankings/world-cup-2026-every-squad-ranked-market-value",
      "primary_source": "https://www.transfermarkt.com/weltmeisterschaft/teilnehmer/pokalwettbewerb/FIWC/saison_id/2025",
      "confidence": 0.85,
      "reviewed_by": "liudehua",
      "source_tier": "secondary_with_primary_reference",
      "primary_source_review_status": "pending_primary_review",
      "confidence_reason": "Secondary published list citing Transfermarkt; not directly re-verified against primary source in this artifact."
    },
    {
      "team_id": "5530",
      "team_name": "Curacao (Curaçao)",
      "squad_value_eur": 25780000,
      "currency": "EUR",
      "observed_at": "2026-06-27T00:00:00Z",
      "source_system": "transfermarkt",
      "source_url": "https://www.planetfootball.com/lists-and-rankings/world-cup-2026-every-squad-ranked-market-value",
      "primary_source": "https://www.transfermarkt.com/weltmeisterschaft/teilnehmer/pokalwettbewerb/FIWC/saison_id/2025",
      "confidence": 0.85,
      "reviewed_by": "liudehua",
      "source_tier": "secondary_with_primary_reference",
      "primary_source_review_status": "pending_primary_review",
      "confidence_reason": "Secondary published list citing Transfermarkt; not directly re-verified against primary source in this artifact."
    },
    {
      "team_id": "1567",
      "team_name": "Iraq",
      "squad_value_eur": 21200000,
      "currency": "EUR",
      "observed_at": "2026-06-27T00:00:00Z",
      "source_system": "transfermarkt",
      "source_url": "https://www.planetfootball.com/lists-and-rankings/world-cup-2026-every-squad-ranked-market-value",
      "primary_source": "https://www.transfermarkt.com/weltmeisterschaft/teilnehmer/pokalwettbewerb/FIWC/saison_id/2025",
      "confidence": 0.85,
      "reviewed_by": "liudehua",
      "source_tier": "secondary_with_primary_reference",
      "primary_source_review_status": "pending_primary_review",
      "confidence_reason": "Secondary published list citing Transfermarkt; not directly re-verified against primary source in this artifact."
    },
    {
      "team_id": "1548",
      "team_name": "Jordan",
      "squad_value_eur": 20300000,
      "currency": "EUR",
      "observed_at": "2026-06-27T00:00:00Z",
      "source_system": "transfermarkt",
      "source_url": "https://www.planetfootball.com/lists-and-rankings/world-cup-2026-every-squad-ranked-market-value",
      "primary_source": "https://www.transfermarkt.com/weltmeisterschaft/teilnehmer/pokalwettbewerb/FIWC/saison_id/2025",
      "confidence": 0.85,
      "reviewed_by": "liudehua",
      "source_tier": "secondary_with_primary_reference",
      "primary_source_review_status": "pending_primary_review",
      "confidence_reason": "Secondary published list citing Transfermarkt; not directly re-verified against primary source in this artifact."
    }
  ],
  "confidence_policy": {
    "primary_reviewed": {
      "max_confidence": 0.95,
      "description": "Direct human review against the primary source page."
    },
    "secondary_with_primary_reference": {
      "max_confidence": 0.85,
      "description": "Reviewed secondary publication citing a primary source; primary source URL retained for later direct review."
    }
  },
  "primary_review_status": "pending_primary_review",
  "next_review_schedule": [
    "after_group_stage",
    "before_knockouts"
  ]
}
